pydaynight/__init__.py
pydaynight/_version.py
pydaynight/pydaynight.py
pyday_night-0.2.1.dist-info/LICENSE
pyday_night-0.2.1.dist-info/METADATA
pyday_night-0.2.1.dist-info/WHEEL
pyday_night-0.2.1.dist-info/top_level.txt
pyday_night-0.2.1.dist-info/RECORD
