Metadata-Version: 2.1
Name: pyday-night
Version: 0.2.1
Summary: Tools for working with the Day-Night Terminator
Home-page: UNKNOWN
Author: David Richardson
Author-email: drichardson42@gatech.edu
License: UNKNOWN
Platform: UNKNOWN
Classifier: Programming Language :: Python :: 3
Classifier: License :: OSI Approved :: MIT License
Classifier: Development Status :: 2 - Pre-Alpha
Classifier: Intended Audience :: Science/Research
Classifier: Operating System :: OS Independent
License-File: LICENSE
Requires-Dist: numpy
Requires-Dist: numba
Provides-Extra: dev
Requires-Dist: twine ; extra == 'dev'
Provides-Extra: test
Requires-Dist: pytest ; extra == 'test'
